daisy_sms/__init__.py
daisy_sms/client.py
daisy_sms/service.py
daisy_sms/exceptions/__init__.py
daisy_sms/exceptions/bad_service.py
daisy_sms/exceptions/invalid_api_key.py
daisy_sms/exceptions/max_price_exceeded.py
daisy_sms/exceptions/no_numbers_left.py
daisy_sms/exceptions/not_enough_balance_left.py
daisy_sms/exceptions/rental_missing.py
daisy_sms/exceptions/too_many_active_rentals.py
daisy_sms/exceptions/wrong_rental_id.py
daisy_sms/models/__init__.py
daisy_sms/models/activation_status.py
daisy_sms/models/get_code_response.py
daisy_sms/models/get_prices_response.py
daisy_sms/models/rent_number_response.py
daisy_sms-1.0.2.dist-info/LICENSE
daisy_sms-1.0.2.dist-info/METADATA
daisy_sms-1.0.2.dist-info/WHEEL
daisy_sms-1.0.2.dist-info/top_level.txt
daisy_sms-1.0.2.dist-info/RECORD
