Metadata-Version: 2.1
Name: daisy-sms
Version: 1.0.2
Summary: simple daisy sms api wrapper
Author-email: olezx <olekzx@python.com>
Project-URL: Homepage, https://github.com/olekzx/daisy-sms
Project-URL: Bug Tracker, https://github.com/olekzx/daisy-sms/issues
Keywords: python,daisy,daisysms,sms,api,wrapper
Classifier: License :: OSI Approved :: MIT License
Classifier: Programming Language :: Python
Classifier: Programming Language :: Python :: 3
Requires-Python: >=3.10
License-File: LICENSE
Requires-Dist: requests>=2.28.2
